{
  "name": "Guy Choosing Two Options",
  "tags": [
    "choice",
    "decision",
    "two-option",
    "indecision"
  ],
  "category": "choice",
  "slots": [
    {
      "name": "left",
      "rect": [
        36,
        35,
        528,
        188
      ],
      "hint": "first option"
    },
    {
      "name": "right",
      "rect": [
        636,
        35,
        528,
        188
      ],
      "hint": "second option"
    }
  ],
  "source": {
    "url": "https://imgflip.com/memetemplate/370327765/Guy-Choosing-Two-Options",
    "license": "fair-use",
    "attribution": "via Imgflip"
  }
}
